dongho_test/__init__.py
dongho_test/test.py
dongho_test-0.2.dist-info/METADATA
dongho_test-0.2.dist-info/WHEEL
dongho_test-0.2.dist-info/top_level.txt
dongho_test-0.2.dist-info/RECORD
